LICENSE.txt
README.rst
pyproject.toml
openet/__init__.py
openet/refetgee/__init__.py
openet/refetgee/calcs.py
openet/refetgee/daily.py
openet/refetgee/hourly.py
openet/refetgee/units.py
openet/refetgee/tests/conftest.py
openet/refetgee/tests/test_calcs.py
openet/refetgee/tests/test_daily.py
openet/refetgee/tests/test_daily_refet_output.py
openet/refetgee/tests/test_hourly.py
openet/refetgee/tests/test_hourly_refet_output.py
openet/refetgee/tests/test_units.py
openet/refetgee/tests/utils.py
openet/refetgee/tests/data/__init__.py
openet/refetgee/tests/data/setup_test_data.py
openet_refet_gee.egg-info/PKG-INFO
openet_refet_gee.egg-info/SOURCES.txt
openet_refet_gee.egg-info/dependency_links.txt
openet_refet_gee.egg-info/requires.txt
openet_refet_gee.egg-info/top_level.txt