Metadata-Version: 2.4
Name: openet-refet-gee
Version: 0.7.1
Summary: Google Earth Engine based ASCE Standardized Reference Evapotranspiration Functions
Author-email: Charles Morton <charles.morton@dri.edu>
License:                                  Apache License
Project-URL: Homepage, https://github.com/Open-ET/openet-refet-gee
Keywords: RefET,OpenET,Earth Engine,evapotranspiration
Classifier: Programming Language :: Python :: 3
Classifier: License :: OSI Approved :: Apache Software License
Classifier: Operating System :: OS Independent
Requires-Python: >=3.9
License-File: LICENSE.txt
Requires-Dist: earthengine-api>=1.5.2
Provides-Extra: test
Requires-Dist: pytest; extra == "test"
Requires-Dist: pandas; extra == "test"
Requires-Dist: pytz; extra == "test"
Dynamic: license-file
